pynslib/.DS_Store
pynslib/__init__.py
pynslib/async/__init__.py
pynslib/async/modules/__init__.py
pynslib/async/modules/parser.py
pynslib/sync/__init__.py
pynslib/sync/api.py
pynslib/sync/modules/__init__.py
pynslib/sync/modules/models.py
pynslib/sync/modules/parser.py
pynslib-0.1.3.dist-info/LICENSE
pynslib-0.1.3.dist-info/WHEEL
pynslib-0.1.3.dist-info/METADATA
pynslib-0.1.3.dist-info/RECORD
